Metadata-Version: 1.1
Name: EconomyCord
Version: 0.0.6
Summary: A simple-compact economy package for discord.py with documentation
Home-page: https://docs.economycord.xyz
Author: Lukas Canter
Author-email: lukascanter07@outlook.com
License: MIT
Keywords: discord.py
Platform: UNKNOWN
Classifier: Development Status :: 5 - Production/Stable
Classifier: Intended Audience :: Developers
Classifier: Operating System :: Microsoft :: Windows :: Windows 10
Classifier: License :: OSI Approved :: MIT License
Classifier: Programming Language :: Python :: 3
